{"data":[{"num":1101,"num_type":"cn","href":"https://v.qq.com/x/cover/53q0eh78q97e4d1/i0042vbez2s.html","title":"第1101话 肉汤是赌上性命的暗号"},{"num":1102,"num_type":"cn","href":"https://v.qq.com/x/cover/53q0eh78q97e4d1/p0043f7wta5.html","title":"第1102话 遭天谴的生日宴（上）"},{"num":1103,"num_type":"cn","href":"https://v.qq.com/x/cover/53q0eh78q97e4d1/r00437zbo11.html","title":"第1103话 遭天谴的生日宴（下）"},{"num":1104,"num_type":"cn","href":"https://v.qq.com/x/cover/53q0eh78q97e4d1/e0043t2njst.html","title":"第1104话 红色绵羊的可怕游戏（上集）"}],"next":"qq-1001-765c3a09"}