{"data":[{"aired_at":"2021-03-13","num_jp":1001,"num_cn":[1058],"manga":["Vol.7"],"title_jp":"ピアノソナタ『月光』殺人事件（後編）","title_cn":"钢琴奏鸣曲“月光”杀人事件（下集） （重制版）"},{"aired_at":"2021-04-17","num_jp":1002,"num_cn":[1059],"manga":["动画原创"],"title_jp":"米花商店街ダストミステリー","title_cn":"米花商店街的垃圾之谜"},{"aired_at":"2021-04-24","num_jp":1003,"num_cn":[1060],"manga":["Vol.97"],"title_jp":"36マスの完全犯罪（前編）","title_cn":"36方格的完美犯罪（上集）"},{"aired_at":"2021-05-01","num_jp":1004,"num_cn":[1061],"manga":["Vol.97"],"title_jp":"36マスの完全犯罪（中編）","title_cn":"36方格的完美犯罪（中集）"},{"aired_at":"2021-05-08","num_jp":1005,"num_cn":[1062],"manga":["Vol.97"],"title_jp":"36マスの完全犯罪（後編）","title_cn":"36方格的完美犯罪（下集）"},{"aired_at":"2021-05-15","num_jp":1006,"num_cn":[1063],"manga":["动画原创"],"title_jp":"毒を入れたのは誰","title_cn":"谁是投毒者？"},{"aired_at":"2021-06-05","num_jp":1007,"num_cn":[1064],"manga":["动画原创"],"title_jp":"復讐者（前編）","title_cn":"复仇者（上集）"},{"aired_at":"2021-06-12","num_jp":1008,"num_cn":[1065],"manga":["动画原创"],"title_jp":"復讐者（後編）","title_cn":"复仇者（下集）"},{"aired_at":"2021-06-19","num_jp":1009,"num_cn":[1066],"manga":["动画原创"],"title_jp":"落とし物は事件のにおい","title_cn":"遗失物背后的案件"},{"aired_at":"2021-06-26","num_jp":1010,"num_cn":[1067],"manga":["动画原创"],"title_jp":"笑顔を消したアイドル","title_cn":"失去笑容的偶像"},{"aired_at":"2021-07-10","num_jp":1011,"num_cn":[1068],"manga":["Vol.97"],"title_jp":"山菜狩りとクローバー（前編）","title_cn":"采野菜和四叶草（上集）"},{"aired_at":"2021-07-17","num_jp":1012,"num_cn":[1069],"manga":["Vol.97"],"title_jp":"山菜狩りとクローバー（後編）","title_cn":"采野菜和四叶草（下集）"},{"aired_at":"2021-07-24","num_jp":1013,"num_cn":[1070],"manga":["动画原创"],"title_jp":"愛しすぎた男","title_cn":"太过深爱的男人"},{"aired_at":"2021-07-31","num_jp":1014,"num_cn":[1071],"manga":["动画原创"],"title_jp":"魔王と呼ばれた小説家","title_cn":"人称魔王的小说家"},{"aired_at":"2021-08-14","num_jp":1015,"num_cn":[1072],"manga":["动画原创"],"title_jp":"張り込み","title_cn":"暗中监视"},{"aired_at":"2021-08-28","num_jp":1016,"num_cn":[1073],"manga":["动画原创"],"title_jp":"モノレール狙撃事件（前編）","title_cn":"单轨列车狙击事件（上集）"},{"aired_at":"2021-09-04","num_jp":1017,"num_cn":[1074],"manga":["动画原创"],"title_jp":"モノレール狙撃事件（後編）","title_cn":"单轨列车狙击事件（下集）"},{"aired_at":"2021-09-11","num_jp":1018,"num_cn":[1075],"manga":["Vol.97~98"],"title_jp":"骨董盆は隠せない（前編）","title_cn":"无法隐藏的古董盘（上集）"},{"aired_at":"2021-09-18","num_jp":1019,"num_cn":[1076],"manga":["Vol.97~98"],"title_jp":"骨董盆は隠せない（中編）","title_cn":"无法隐藏的古董盘（中集）"},{"aired_at":"2021-09-25","num_jp":1020,"num_cn":[1077],"manga":["Vol.97~98"],"title_jp":"骨董盆は隠せない（後編）","title_cn":"无法隐藏的古董盘（下集）"}],"next":"episode-501-0957c2eb"}